schedint/__init__.py
schedint/cli.py
schedint/core.py
schedint-0.0.1.dist-info/licenses/LICENSE
schedint-0.0.1.dist-info/METADATA
schedint-0.0.1.dist-info/WHEEL
schedint-0.0.1.dist-info/entry_points.txt
schedint-0.0.1.dist-info/top_level.txt
schedint-0.0.1.dist-info/RECORD
