Metadata-Version: 2.4
Name: schedint
Version: 0.0.1
Summary: Jodrell bank pulsar schedule editor
Author: Benjamin Shaw
License: Copyright 2026 University of Manchester
Requires-Python: >=3.7
License-File: LICENSE
Provides-Extra: dev
Requires-Dist: pytest; extra == "dev"
Requires-Dist: tox; extra == "dev"
Requires-Dist: flake8; extra == "dev"
Requires-Dist: build; extra == "dev"
Requires-Dist: twine; extra == "dev"
Dynamic: license-file
